pakler/__init__.py
pakler/__main__.py
pakler/_version.py
pakler-0.2.0.dist-info/LICENSE
pakler-0.2.0.dist-info/METADATA
pakler-0.2.0.dist-info/WHEEL
pakler-0.2.0.dist-info/entry_points.txt
pakler-0.2.0.dist-info/top_level.txt
pakler-0.2.0.dist-info/RECORD
