Metadata-Version: 2.1
Name: pakler
Version: 0.2.0
Summary: Manipulate .PAK firmware files from Swann and Reolink
Author-email: Vincent Mallet <vmallet@gmail.com>
License: MIT License
Project-URL: Homepage, https://github.com/vmallet/pakler
Project-URL: Issues, https://github.com/vmallet/pakler/issues
Keywords: swann,reolink,firmware,pak
Classifier: Development Status :: 4 - Beta
Classifier: Intended Audience :: Developers
Classifier: License :: OSI Approved :: MIT License
Classifier: Operating System :: OS Independent
Classifier: Programming Language :: Python
Classifier: Programming Language :: Python :: 3
Classifier: Programming Language :: Python :: 3 :: Only
Classifier: Programming Language :: Python :: 3.6
Classifier: Programming Language :: Python :: 3.7
Classifier: Programming Language :: Python :: 3.8
Classifier: Programming Language :: Python :: 3.9
Classifier: Programming Language :: Python :: 3.10
Classifier: Programming Language :: Python :: 3.11
Classifier: Topic :: Software Development :: Libraries
Classifier: Topic :: Software Development :: Libraries :: Python Modules
Classifier: Topic :: Utilities
Requires-Python: >=3.6
License-File: LICENSE
